Workbook

Sheet Cleaned Data
A1: order_id | B1: Product_category_cleaned | C1: origin_city | D1: destination_city.1 | E1: destination_state | F1: logistics_provider_name | G1: final_delivery_status | H1: Payment Mode | I1: Sources | J1: dispatch_date | K1: actual_delivery_date | L1: promised_delivery_date | M1: Delivery Days | N1: transit_storage_cost | O1: Helper_transit | P1: shipping_cost | Q1: Session_length
A2: 977567 | B2: Laptop | C2: Delhi | D2: Delhi | E2: DL | F2: FastWheels Ltd | G2: Delivered | H2: Credit Card | I2: App | J2: 43525.173 | K2: 43525.173 | L2: 43528.173 | M2: =_xlfn.DAYS(Table1[[#This Row],[actual_delivery_date]],Table1[[#This Row],[dispatch_date]]) -> 0 | N2: 0 | O2: =Table1[[#This Row],[transit_storage_cost]] * (1-'What -if Analysis'!$D$26) -> 0 | P2: 108 | Q2: 558.88768
A3: 703560 | B3: Mobile | C3: Delhi | D3: Delhi | E3: DL | F3: FastWheels Ltd | G3: Delivered | H3: Debit Card | I3: Website | J3: 43525.305 | K3: 43525.305 | L3: 43529.305 | M3: =_xlfn.DAYS(Table1[[#This Row],[actual_delivery_date]],Table1[[#This Row],[dispatch_date]]) -> 0 | N3: 0 | O3: =Table1[[#This Row],[transit_storage_cost]] * (1-'What -if Analysis'!$D$26) -> 0 | P3: 123 | Q3: 766
A4: 783549 | B4: Laptop | C4: Delhi | D4: Delhi | E4: DL | F4: FastWheels Ltd | G4: Returned | H4: Credit Card | I4: Website | J4: 43525.343 | K4: 43525.343 | L4: 43532.343 | M4: =_xlfn.DAYS(Table1[[#This Row],[actual_delivery_date]],Table1[[#This Row],[dispatch_date]]) -> 0 | N4: 0 | O4: =Table1[[#This Row],[transit_storage_cost]] * (1-'What -if Analysis'!$D$26) -> 0 | P4: 103 | Q4: 2763.7691
A5: 698253 | B5: Laptop | C5: Bangalore | D5: Bangalore | E5: KA | F5: FastWheels Ltd | G5: Delivered | H5: Credit Card | I5: Website | J5: 43525.388 | K5: 43525.388 | L5: 43530.388 | M5: =_xlfn.DAYS(Table1[[#This Row],[actual_delivery_date]],Table1[[#This Row],[dispatch_date]]) -> 0 | N5: 0 | O5: =Table1[[#This Row],[transit_storage_cost]] * (1-'What -if Analysis'!$D$26) -> 0 | P5: 108 | Q5: 2376.71
A6: 731550 | B6: Mobile | C6: Bangalore | D6: Bangalore | E6: KA | F6: FastWheels Ltd | G6: Delivered | H6: Debit Card | I6: Website | J6: 43525.388 | K6: 43525.388 | L6: 43532.388 | M6: =_xlfn.DAYS(Table1[[#This Row],[actual_delivery_date]],Table1[[#This Row],[dispatch_date]]) -> 0 | N6: 0 | O6: =Table1[[#This Row],[transit_storage_cost]] * (1-'What -if Analysis'!$D$26) -> 0 | P6: 108 | Q6: 1684.43
A7: 421910 | B7: Laptop | C7: Delhi | D7: Delhi | E7: DL | F7: FastWheels Ltd | G7: Delivered | H7: Debit Card | I7: App | J7: 43525.425 | K7: 43525.425 | L7: 43528.425 | M7: =_xlfn.DAYS(Table1[[#This Row],[actual_delivery_date]],Table1[[#This Row],[dispatch_date]]) -> 0 | N7: 0 | O7: =Table1[[#This Row],[transit_storage_cost]] * (1-'What -if Analysis'!$D$26) -> 0 | P7: 108 | Q7: 2478.4656
A8: 526095 | B8: Mobile | C8: Delhi | D8: Delhi | E8: DL | F8: FastWheels Ltd | G8: Delivered | H8: Credit Card | I8: Website | J8: 43525.454 | K8: 43525.454 | L8: 43530.454 | M8: =_xlfn.DAYS(Table1[[#This Row],[actual_delivery_date]],Table1[[#This Row],[dispatch_date]]) -> 0 | N8: 0 | O8: =Table1[[#This Row],[transit_storage_cost]] * (1-'What -if Analysis'!$D$26) -> 0 | P8: 104 | Q8: 3387.3
A9: 469838 | B9: Mobile | C9: Bangalore | D9: Bangalore | E9: KA | F9: Ship2Home Logistics Unit | G9: Delivered | H9: Debit Card | I9: App | J9: 43525.455 | K9: 43525.455 | L9: 43532.455 | M9: =_xlfn.DAYS(Table1[[#This Row],[actual_delivery_date]],Table1[[#This Row],[dispatch_date]]) -> 0 | N9: 0 | O9: =Table1[[#This Row],[transit_storage_cost]] * (1-'What -if Analysis'!$D$26) -> 0 | P9: 130 | Q9: 3461.6871
A10: 208180 | B10: Mobile | C10: Bangalore | D10: Bangalore | E10: KA | F10: FastWheels Ltd | G10: Delivered | H10: Debit Card | I10: App | J10: 43525.747 | K10: 43525.747 | L10: 43531.747 | M10: =_xlfn.DAYS(Table1[[#This Row],[actual_delivery_date]],Table1[[#This Row],[dispatch_date]]) -> 0 | N10: 0 | O10: =Table1[[#This Row],[transit_storage_cost]] * (1-'What -if Analysis'!$D$26) -> 0 | P10: 125 | Q10: 2910.9519
A11: 253533 | B11: Mobile | C11: Bangalore | D11: Bangalore | E11: KA | F11: FastWheels Ltd | G11: Delivered | H11: Cash On Delivery | I11: Website | J11: 43525.866 | K11: 43525.866 | L11: 43531.866 | M11: =_xlfn.DAYS(Table1[[#This Row],[actual_delivery_date]],Table1[[#This Row],[dispatch_date]]) -> 0 | N11: 0 | O11: =Table1[[#This Row],[transit_storage_cost]] * (1-'What -if Analysis'!$D$26) -> 0 | P11: 101 | Q11: 3254.26
A12: 379572 | B12: PC | C12: Delhi | D12: Delhi | E12: DL | F12: FastWheels Ltd | G12: Delivered | H12: Debit Card | I12: Website | J12: 43526.047 | K12: 43526.047 | L12: 43529.047 | M12: =_xlfn.DAYS(Table1[[#This Row],[actual_delivery_date]],Table1[[#This Row],[dispatch_date]]) -> 0 | N12: 0 | O12: =Table1[[#This Row],[transit_storage_cost]] * (1-'What -if Analysis'!$D$26) -> 0 | P12: 101 | Q12: 2133.03
A13: 438274 | B13: Laptop | C13: Bangalore | D13: Bangalore | E13: KA | F13: Ship2Home Logistics Unit | G13: Delivered | H13: Debit Card | I13: App | J13: 43525.055 | K13: 43526.055 | L13: 43531.055 | M13: =_xlfn.DAYS(Table1[[#This Row],[actual_delivery_date]],Table1[[#This Row],[dispatch_date]]) -> 1 | N13: 0 | O13: =Table1[[#This Row],[transit_storage_cost]] * (1-'What -if Analysis'!$D$26) -> 0 | P13: 122 | Q13: 1547.3549
... A161: 463167 | B161: Tablet | C161: Delhi | D161: Bangalore | E161: KA | F161: FastWheels Ltd | G161: Delivered | H161: Credit Card | I161: Website | J161: 43526.498 | K161: 43528.498 | L161: 43531.498 | M161: =_xlfn.DAYS(Table1[[#This Row],[actual_delivery_date]],Table1[[#This Row],[dispatch_date]]) -> 2 | N161: 64 | O161: =Table1[[#This Row],[transit_storage_cost]] * (1-'What -if Analysis'!$D$26) -> 64 | P161: 105 | Q161: 3591.7
A162: 834190 | B162: Laptop | C162: Delhi | D162: Bangalore | E162: KA | G162: Delivered | H162: Debit Card | I162: App | J162: 43526.5 | K162: 43528.5 | L162: 43533.5 | M162: =_xlfn.DAYS(Table1[[#This Row],[actual_delivery_date]],Table1[[#This Row],[dispatch_date]]) -> 2 | N162: 31 | O162: =Table1[[#This Row],[transit_storage_cost]] * (1-'What -if Analysis'!$D$26) -> 31 | P162: 128 | Q162: 3311.7521
A163: 836756 | B163: PC | C163: Bangalore | D163: Kolkata | E163: WB | F163: FastWheels Ltd | G163: Delivered | H163: Debit Card | I163: App | J163: 43525.501 | K163: 43528.501 | L163: 43531.501 | M163: =_xlfn.DAYS(Table1[[#This Row],[actual_delivery_date]],Table1[[#This Row],[dispatch_date]]) -> 3 | N163: 26 | O163: =Table1[[#This Row],[transit_storage_cost]] * (1-'What -if Analysis'!$D$26) -> 26 | P163: 115 | Q163: 586.91424
A164: 473212 | B164: Laptop | C164: Delhi | D164: Delhi | E164: DL | F164: FastWheels Ltd | G164: Delivered | H164: Debit Card | I164: App | J164: 43525.504 | K164: 43528.504 | L164: 43528.504 | M164: =_xlfn.DAYS(Table1[[#This Row],[actual_delivery_date]],Table1[[#This Row],[dispatch_date]]) -> 3 | N164: 0 | O164: =Table1[[#This Row],[transit_storage_cost]] * (1-'What -if Analysis'!$D$26) -> 0 | P164: 126 | Q164: 3113.819
A165: 260810 | B165: Gaming Console | C165: Delhi | D165: Mumbai | E165: MH | F165: FastWheels Ltd | G165: Delivered | H165: Debit Card | I165: App | J165: 43526.508 | K165: 43528.508 | L165: 43531.508 | M165: =_xlfn.DAYS(Table1[[#This Row],[actual_delivery_date]],Table1[[#This Row],[dispatch_date]]) -> 2 | N165: 71 | O165: =Table1[[#This Row],[transit_storage_cost]] * (1-'What -if Analysis'!$D$26) -> 71 | P165: 92 | Q165: 2600.7327
A166: 276378 | B166: Mobile | C166: Bangalore | D166: Mumbai | E166: MH | F166: FastWheels Ltd | G166: Delivered | H166: Debit Card | I166: Website | J166: 43526.517 | K166: 43528.517 | L166: 43532.517 | M166: =_xlfn.DAYS(Table1[[#This Row],[actual_delivery_date]],Table1[[#This Row],[dispatch_date]]) -> 2 | N166: 71 | O166: =Table1[[#This Row],[transit_storage_cost]] * (1-'What -if Analysis'!$D$26) -> 71 | P166: 94 | Q166: 1334.86
A167: 11940 | B167: Mobile | C167: Delhi | D167: Bangalore | E167: KA | F167: FastWheels Ltd | G167: Delivered | H167: Debit Card | I167: Website | J167: 43526.526 | K167: 43528.526 | L167: 43530.526 | M167: =_xlfn.DAYS(Table1[[#This Row],[actual_delivery_date]],Table1[[#This Row],[dispatch_date]]) -> 2 | N167: 40 | O167: =Table1[[#This Row],[transit_storage_cost]] * (1-'What -if Analysis'!$D$26) -> 40 | P167: 125 | Q167: 1802.29
A168: 601672 | B168: Tablet | C168: Delhi | D168: Kolkata | E168: WB | F168: FastWheels Ltd | G168: Delivered | H168: Debit Card | I168: App | J168: 43525.533 | K168: 43528.533 | L168: 43530.533 | M168: =_xlfn.DAYS(Table1[[#This Row],[actual_delivery_date]],Table1[[#This Row],[dispatch_date]]) -> 3 | N168: 28 | O168: =Table1[[#This Row],[transit_storage_cost]] * (1-'What -if Analysis'!$D$26) -> 28 | P168: 106 | Q168: 990.00048
A169: 707752 | B169: Tablet | C169: Delhi | D169: Mumbai | E169: MH | F169: FastWheels Ltd | G169: Delivered | H169: Debit Card | I169: App | J169: 43525.549 | K169: 43528.549 | L169: 43529.549 | M169: =_xlfn.DAYS(Table1[[#This Row],[actual_delivery_date]],Table1[[#This Row],[dispatch_date]]) -> 3 | N169: 86 | O169: =Table1[[#This Row],[transit_storage_cost]] * (1-'What -if Analysis'!$D$26) -> 86 | P169: 86 | Q169: 3517.3202
A170: 655078 | B170: Mobile | C170: Bangalore | D170: Kolkata | E170: WB | F170: Ship2Home Logistics Unit | G170: Delivered | H170: Debit Card | I170: App | J170: 43526.55 | K170: 43528.55 | L170: 43529.55 | M170: =_xlfn.DAYS(Table1[[#This Row],[actual_delivery_date]],Table1[[#This Row],[dispatch_date]]) -> 2 | N170: 39 | O170: =Table1[[#This Row],[transit_storage_cost]] * (1-'What -if Analysis'!$D$26) -> 39 | P170: 108 | Q170: 2939.1285
A171: 62892 | B171: Laptop | C171: Bangalore | D171: Mumbai | E171: MH | F171: FastWheels Ltd | G171: Delivered | H171: Debit Card | I171: Website | J171: 43526.559 | K171: 43528.559 | L171: 43532.559 | M171: =_xlfn.DAYS(Table1[[#This Row],[actual_delivery_date]],Table1[[#This Row],[dispatch_date]]) -> 2 | N171: 70 | O171: =Table1[[#This Row],[transit_storage_cost]] * (1-'What -if Analysis'!$D$26) -> 70 | P171: 95 | Q171: 2826.98
A172: 13342 | B172: Tablet | C172: Bangalore | D172: Delhi | E172: DL | F172: FastWheels Ltd | G172: Delivered | H172: Debit Card | I172: App | J172: 43526.564 | K172: 43528.564 | L172: 43529.564 | M172: =_xlfn.DAYS(Table1[[#This Row],[actual_delivery_date]],Table1[[#This Row],[dispatch_date]]) -> 2 | N172: 67 | O172: =Table1[[#This Row],[transit_storage_cost]] * (1-'What -if Analysis'!$D$26) -> 67 | P172: 106 | Q172: 3656.1546
A173: 319442 | B173: Mobile | C173: Bangalore | D173: Chennai | E173: TN | F173: Ship2Home Logistics Unit | G173: Returned | H173: Debit Card | I173: App | J173: 43526.603 | K173: 43528.603 | L173: 43532.603 | M173: =_xlfn.DAYS(Table1[[#This Row],[actual_delivery_date]],Table1[[#This Row],[dispatch_date]]) -> 2 | N173: 31 | O173: =Table1[[#This Row],[transit_storage_cost]] * (1-'What -if Analysis'!$D$26) -> 31 | P173: 128 | Q173: 3456.4382
A174: 519269 | B174: TV | C174: Delhi | D174: Delhi | E174: DL | F174: Ship2Home delivery | G174: Delivered | H174: Credit Card | I174: App | J174: 43525.618 | K174: 43528.618 | L174: 43530.618 | M174: =_xlfn.DAYS(Table1[[#This Row],[actual_delivery_date]],Table1[[#This Row],[dispatch_date]]) -> 3 | N174: 0 | O174: =Table1[[#This Row],[transit_storage_cost]] * (1-'What -if Analysis'!$D$26) -> 0 | P174: 126 | Q174: 417.20076
... A934: 454739 | B934: PC | C934: Bangalore | D934: Delhi | E934: DL | F934: Ship2Home delivery | G934: Delivered | H934: Credit Card | I934: App | J934: 43528.312 | K934: 43532.312 | L934: 43531.312 | M934: =_xlfn.DAYS(Table1[[#This Row],[actual_delivery_date]],Table1[[#This Row],[dispatch_date]]) -> 4 | N934: 35 | O934: =Table1[[#This Row],[transit_storage_cost]] * (1-'What -if Analysis'!$D$26) -> 35 | P934: 125 | Q934: 1804.7607
A935: 543275 | B935: TV | C935: Delhi | D935: Mumbai | E935: MH | G935: Delivered | H935: Credit Card | I935: App | J935: 43530.318 | K935: 43532.318 | L935: 43536.318 | M935: =_xlfn.DAYS(Table1[[#This Row],[actual_delivery_date]],Table1[[#This Row],[dispatch_date]]) -> 2 | N935: 49 | O935: =Table1[[#This Row],[transit_storage_cost]] * (1-'What -if Analysis'!$D$26) -> 49 | P935: 111 | Q935: 2312.745
A936: 58385 | B936: Tablet | C936: Delhi | D936: Chennai | E936: TN | F936: Ship2Home delivery | G936: Delivered | H936: Credit Card | I936: App | J936: 43526.321 | K936: 43532.321 | L936: 43531.321 | M936: =_xlfn.DAYS(Table1[[#This Row],[actual_delivery_date]],Table1[[#This Row],[dispatch_date]]) -> 6 | N936: 40 | O936: =Table1[[#This Row],[transit_storage_cost]] * (1-'What -if Analysis'!$D$26) -> 40 | P936: 123 | Q936: 3002.8836
A937: 458152 | B937: PC | C937: Delhi | D937: Chennai | E937: TN | F937: FastWheels Ltd | G937: Delivered | H937: Debit Card | I937: App | J937: 43525.326 | K937: 43532.326 | L937: 43531.326 | M937: =_xlfn.DAYS(Table1[[#This Row],[actual_delivery_date]],Table1[[#This Row],[dispatch_date]]) -> 7 | N937: 41 | O937: =Table1[[#This Row],[transit_storage_cost]] * (1-'What -if Analysis'!$D$26) -> 41 | P937: 127 | Q937: 3365.0038
A938: 904751 | B938: Laptop | C938: Bangalore | D938: Kolkata | E938: WB | F938: FastWheels Ltd | G938: Delivered | H938: Credit Card | I938: App | J938: 43527.327 | K938: 43532.327 | L938: 43533.327 | M938: =_xlfn.DAYS(Table1[[#This Row],[actual_delivery_date]],Table1[[#This Row],[dispatch_date]]) -> 5 | N938: 65 | O938: =Table1[[#This Row],[transit_storage_cost]] * (1-'What -if Analysis'!$D$26) -> 65 | P938: 89 | Q938: 1011.3207
A939: 127447 | B939: Tablet | C939: Delhi | D939: Delhi | E939: DL | F939: Ship2Home delivery | G939: Delivered | H939: Credit Card | I939: App | J939: 43530.336 | K939: 43532.336 | L939: 43537.336 | M939: =_xlfn.DAYS(Table1[[#This Row],[actual_delivery_date]],Table1[[#This Row],[dispatch_date]]) -> 2 | N939: 0 | O939: =Table1[[#This Row],[transit_storage_cost]] * (1-'What -if Analysis'!$D$26) -> 0 | P939: 128 | Q939: 1440.33
A940: 143957 | B940: PC | C940: Delhi | D940: Delhi | E940: DL | F940: Ship2Home delivery | G940: Delivered | H940: Credit Card | I940: App | J940: 43526.34 | K940: 43532.34 | L940: 43529.34 | M940: =_xlfn.DAYS(Table1[[#This Row],[actual_delivery_date]],Table1[[#This Row],[dispatch_date]]) -> 6 | N940: 0 | O940: =Table1[[#This Row],[transit_storage_cost]] * (1-'What -if Analysis'!$D$26) -> 0 | P940: 124 | Q940: 2165.7016
A941: 453223 | B941: TV | C941: Delhi | D941: Kolkata | E941: WB | F941: Ship2Home delivery | G941: Delivered | H941: Credit Card | I941: App | J941: 43527.345 | K941: 43532.345 | L941: 43532.345 | M941: =_xlfn.DAYS(Table1[[#This Row],[actual_delivery_date]],Table1[[#This Row],[dispatch_date]]) -> 5 | N941: 40 | O941: =Table1[[#This Row],[transit_storage_cost]] * (1-'What -if Analysis'!$D$26) -> 40 | P941: 106 | Q941: 3325.0129
A942: 125497 | B942: PC | C942: Bangalore | D942: Delhi | E942: DL | F942: Ship2Home delivery | G942: Delivered | H942: Credit Card | I942: App | J942: 43525.345 | K942: 43532.345 | L942: 43528.345 | M942: =_xlfn.DAYS(Table1[[#This Row],[actual_delivery_date]],Table1[[#This Row],[dispatch_date]]) -> 7 | N942: 27 | O942: =Table1[[#This Row],[transit_storage_cost]] * (1-'What -if Analysis'!$D$26) -> 27 | P942: 125 | Q942: 787.72129
A943: 64570 | B943: Laptop | C943: Bangalore | D943: Bangalore | E943: KA | F943: FastWheels Ltd | G943: Delivered | H943: Debit Card | I943: App | J943: 43528.348 | K943: 43532.348 | L943: 43534.348 | M943: =_xlfn.DAYS(Table1[[#This Row],[actual_delivery_date]],Table1[[#This Row],[dispatch_date]]) -> 4 | N943: 0 | O943: =Table1[[#This Row],[transit_storage_cost]] * (1-'What -if Analysis'!$D$26) -> 0 | P943: 103 | Q943: 1762.699
A944: 854355 | B944: Mobile | C944: Delhi | D944: Bangalore | E944: KA | F944: FastWheels Ltd | G944: Delivered | H944: Credit Card | I944: Website | J944: 43530.349 | K944: 43532.349 | L944: 43537.349 | M944: =_xlfn.DAYS(Table1[[#This Row],[actual_delivery_date]],Table1[[#This Row],[dispatch_date]]) -> 2 | N944: 61 | O944: =Table1[[#This Row],[transit_storage_cost]] * (1-'What -if Analysis'!$D$26) -> 61 | P944: 109 | Q944: 3717.8135
A945: 101282 | B945: TV | C945: Delhi | D945: Kolkata | E945: WB | F945: Ship2Home Logistics Unit | G945: Delivered | H945: Debit Card | I945: App | J945: 43527.35 | K945: 43532.35 | L945: 43533.35 | M945: =_xlfn.DAYS(Table1[[#This Row],[actual_delivery_date]],Table1[[#This Row],[dispatch_date]]) -> 5 | N945: 31 | O945: =Table1[[#This Row],[transit_storage_cost]] * (1-'What -if Analysis'!$D$26) -> 31 | P945: 107 | Q945: 2948.1301
A946: 478547 | B946: Mobile | C946: Delhi | D946: Delhi | E946: DL | F946: FastWheels Ltd | G946: Delivered | H946: Credit Card | I946: App | J946: 43527.351 | K946: 43532.351 | L946: 43533.351 | M946: =_xlfn.DAYS(Table1[[#This Row],[actual_delivery_date]],Table1[[#This Row],[dispatch_date]]) -> 5 | N946: 0 | O946: =Table1[[#This Row],[transit_storage_cost]] * (1-'What -if Analysis'!$D$26) -> 0 | P946: 109 | Q946: 2465.473
A947: 352039 | B947: Mobile | C947: Delhi | D947: Delhi | E947: DL | F947: Ship2Home delivery | G947: Delivered | H947: Credit Card | I947: App | J947: 43529.354 | K947: 43532.354 | L947: 43533.354 | M947: =_xlfn.DAYS(Table1[[#This Row],[actual_delivery_date]],Table1[[#This Row],[dispatch_date]]) -> 3 | N947: 0 | O947: =Table1[[#This Row],[transit_storage_cost]] * (1-'What -if Analysis'!$D$26) -> 0 | P947: 124 | Q947: 2877.2485
... A2049: 588089 | B2049: Gaming Console | C2049: Bangalore | D2049: Bangalore | E2049: KA | F2049: Ship2Home delivery | G2049: Delivered | H2049: Credit Card | I2049: App | J2049: 43536.03 | K2049: 43536.03 | L2049: 43540.03 | M2049: =_xlfn.DAYS(Table1[[#This Row],[actual_delivery_date]],Table1[[#This Row],[dispatch_date]]) -> 0 | N2049: 0 | O2049: =Table1[[#This Row],[transit_storage_cost]] * (1-'What -if Analysis'!$D$26) -> 0 | P2049: 127 | Q2049: 1155.8913
A2050: 438826 | B2050: Mobile | C2050: Delhi | D2050: Bangalore | E2050: KA | G2050: Returned | H2050: Debit Card | I2050: App | J2050: 43534.031 | K2050: 43536.031 | L2050: 43537.031 | M2050: =_xlfn.DAYS(Table1[[#This Row],[actual_delivery_date]],Table1[[#This Row],[dispatch_date]]) -> 2 | N2050: 45 | O2050: =Table1[[#This Row],[transit_storage_cost]] * (1-'What -if Analysis'!$D$26) -> 45 | P2050: 125 | Q2050: 634
A2051: 415262 | B2051: Laptop | C2051: Delhi | D2051: Mumbai | E2051: MH | F2051: Ship2Home Logistics Unit | G2051: Delivered | H2051: Debit Card | I2051: App | J2051: 43529.036 | K2051: 43536.036 | L2051: 43532.036 | M2051: =_xlfn.DAYS(Table1[[#This Row],[actual_delivery_date]],Table1[[#This Row],[dispatch_date]]) -> 7 | N2051: 36 | O2051: =Table1[[#This Row],[transit_storage_cost]] * (1-'What -if Analysis'!$D$26) -> 36 | P2051: 115 | Q2051: 2859.1734
A2052: 65086 | B2052: PC | C2052: Bangalore | D2052: Bangalore | E2052: KA | F2052: Ship2Home Logistics Unit | G2052: Delivered | H2052: Debit Card | I2052: App | J2052: 43533.045 | K2052: 43536.045 | L2052: 43536.045 | M2052: =_xlfn.DAYS(Table1[[#This Row],[actual_delivery_date]],Table1[[#This Row],[dispatch_date]]) -> 3 | N2052: 0 | O2052: =Table1[[#This Row],[transit_storage_cost]] * (1-'What -if Analysis'!$D$26) -> 0 | P2052: 122 | Q2052: 2792
A2053: 26807 | B2053: Gaming Console | C2053: Delhi | D2053: Mumbai | E2053: MH | F2053: Ship2Home delivery | G2053: Delivered | H2053: Credit Card | I2053: App | J2053: 43533.046 | K2053: 43536.046 | L2053: 43540.046 | M2053: =_xlfn.DAYS(Table1[[#This Row],[actual_delivery_date]],Table1[[#This Row],[dispatch_date]]) -> 3 | N2053: 28 | O2053: =Table1[[#This Row],[transit_storage_cost]] * (1-'What -if Analysis'!$D$26) -> 28 | P2053: 111 | Q2053: 1164.9945
A2054: 843368 | B2054: PC | C2054: Delhi | D2054: Delhi | E2054: DL | F2054: FastWheels Ltd | G2054: Delivered | H2054: Debit Card | I2054: App | J2054: 43536.05 | K2054: 43536.05 | L2054: 43541.05 | M2054: =_xlfn.DAYS(Table1[[#This Row],[actual_delivery_date]],Table1[[#This Row],[dispatch_date]]) -> 0 | N2054: 0 | O2054: =Table1[[#This Row],[transit_storage_cost]] * (1-'What -if Analysis'!$D$26) -> 0 | P2054: 130 | Q2054: 3305.2821
A2055: 309074 | B2055: Mobile | C2055: Delhi | D2055: Kolkata | E2055: WB | F2055: Ship2Home Logistics Unit | G2055: Delivered | H2055: Debit Card | I2055: App | J2055: 43531.053 | K2055: 43536.053 | L2055: 43536.053 | M2055: =_xlfn.DAYS(Table1[[#This Row],[actual_delivery_date]],Table1[[#This Row],[dispatch_date]]) -> 5 | N2055: 32 | O2055: =Table1[[#This Row],[transit_storage_cost]] * (1-'What -if Analysis'!$D$26) -> 32 | P2055: 111 | Q2055: 1174.3676
A2056: 843607 | B2056: Mobile | C2056: Bangalore | D2056: Mumbai | E2056: MH | F2056: Ship2Home delivery | G2056: Delivered | H2056: Credit Card | I2056: App | J2056: 43529.053 | K2056: 43536.053 | L2056: 43536.053 | M2056: =_xlfn.DAYS(Table1[[#This Row],[actual_delivery_date]],Table1[[#This Row],[dispatch_date]]) -> 7 | N2056: 27 | O2056: =Table1[[#This Row],[transit_storage_cost]] * (1-'What -if Analysis'!$D$26) -> 27 | P2056: 106 | Q2056: 2034.261
A2057: 775117 | B2057: Mobile | C2057: Delhi | D2057: Delhi | E2057: DL | F2057: FastWheels Ltd | G2057: Delivered | H2057: Cash On Delivery | I2057: App | J2057: 43534.057 | K2057: 43536.057 | L2057: 43537.057 | M2057: =_xlfn.DAYS(Table1[[#This Row],[actual_delivery_date]],Table1[[#This Row],[dispatch_date]]) -> 2 | N2057: 0 | O2057: =Table1[[#This Row],[transit_storage_cost]] * (1-'What -if Analysis'!$D$26) -> 0 | P2057: 104 | Q2057: 1100.4247
A2058: 213166 | B2058: TV | C2058: Delhi | D2058: Delhi | E2058: DL | F2058: FastWheels Ltd | G2058: Delivered | H2058: Debit Card | I2058: App | J2058: 43534.058 | K2058: 43536.058 | L2058: 43539.058 | M2058: =_xlfn.DAYS(Table1[[#This Row],[actual_delivery_date]],Table1[[#This Row],[dispatch_date]]) -> 2 | N2058: 0 | O2058: =Table1[[#This Row],[transit_storage_cost]] * (1-'What -if Analysis'!$D$26) -> 0 | P2058: 103 | Q2058: 831.40004
A2059: 736333 | B2059: PC | C2059: Delhi | D2059: Bangalore | E2059: KA | F2059: FastWheels Ltd | G2059: Delivered | H2059: Credit Card | I2059: App | J2059: 43533.061 | K2059: 43536.061 | L2059: 43537.061 | M2059: =_xlfn.DAYS(Table1[[#This Row],[actual_delivery_date]],Table1[[#This Row],[dispatch_date]]) -> 3 | N2059: 70 | O2059: =Table1[[#This Row],[transit_storage_cost]] * (1-'What -if Analysis'!$D$26) -> 70 | P2059: 103 | Q2059: 1532
A2060: 381738 | B2060: TV | C2060: Delhi | D2060: Chennai | E2060: TN | F2060: Ship2Home Logistics Unit | G2060: Delivered | H2060: Debit Card | I2060: Website | J2060: 43530.062 | K2060: 43536.062 | L2060: 43535.062 | M2060: =_xlfn.DAYS(Table1[[#This Row],[actual_delivery_date]],Table1[[#This Row],[dispatch_date]]) -> 6 | N2060: 38 | O2060: =Table1[[#This Row],[transit_storage_cost]] * (1-'What -if Analysis'!$D$26) -> 38 | P2060: 128 | Q2060: 209.58
A2061: 44314 | B2061: TV | C2061: Delhi | D2061: Delhi | E2061: DL | F2061: Ship2Home Logistics Unit | G2061: Delivered | H2061: Debit Card | I2061: App | J2061: 43531.063 | K2061: 43536.063 | L2061: 43536.063 | M2061: =_xlfn.DAYS(Table1[[#This Row],[actual_delivery_date]],Table1[[#This Row],[dispatch_date]]) -> 5 | N2061: 0 | O2061: =Table1[[#This Row],[transit_storage_cost]] * (1-'What -if Analysis'!$D$26) -> 0 | P2061: 120 | Q2061: 368
A2062: 307015 | B2062: Laptop | C2062: Bangalore | D2062: Mumbai | E2062: MH | F2062: FastWheels Ltd | G2062: Delivered | H2062: Credit Card | I2062: App | J2062: 43534.068 | K2062: 43536.068 | L2062: 43541.068 | M2062: =_xlfn.DAYS(Table1[[#This Row],[actual_delivery_date]],Table1[[#This Row],[dispatch_date]]) -> 2 | N2062: 78 | O2062: =Table1[[#This Row],[transit_storage_cost]] * (1-'What -if Analysis'!$D$26) -> 78 | P2062: 85 | Q2062: 2024.7112
... A2763: 306131 | B2763: Mobile | C2763: Bangalore | D2763: Delhi | E2763: DL | F2763: Ship2Home delivery | G2763: Delivered | H2763: Cash On Delivery | I2763: App | J2763: 43532.364 | K2763: 43538.364 | L2763: 43535.364 | M2763: =_xlfn.DAYS(Table1[[#This Row],[actual_delivery_date]],Table1[[#This Row],[dispatch_date]]) -> 6 | N2763: 42 | O2763: =Table1[[#This Row],[transit_storage_cost]] * (1-'What -if Analysis'!$D$26) -> 42 | P2763: 127 | Q2763: 2340.1803
A2764: 928825 | B2764: Mobile | C2764: Delhi | D2764: Chennai | E2764: TN | G2764: Delivered | H2764: Credit Card | I2764: App | J2764: 43536.366 | K2764: 43538.366 | L2764: 43541.366 | M2764: =_xlfn.DAYS(Table1[[#This Row],[actual_delivery_date]],Table1[[#This Row],[dispatch_date]]) -> 2 | N2764: 28 | O2764: =Table1[[#This Row],[transit_storage_cost]] * (1-'What -if Analysis'!$D$26) -> 28 | P2764: 127 | Q2764: 3402.2241
A2765: 105878 | B2765: PC | C2765: Delhi | D2765: Delhi | E2765: DL | F2765: Ship2Home Logistics Unit | G2765: Delivered | H2765: Debit Card | I2765: App | J2765: 43531.369 | K2765: 43538.369 | L2765: 43534.369 | M2765: =_xlfn.DAYS(Table1[[#This Row],[actual_delivery_date]],Table1[[#This Row],[dispatch_date]]) -> 7 | N2765: 0 | O2765: =Table1[[#This Row],[transit_storage_cost]] * (1-'What -if Analysis'!$D$26) -> 0 | P2765: 124 | Q2765: 2658.0461
A2766: 957358 | B2766: PC | C2766: Bangalore | D2766: Bangalore | E2766: KA | F2766: Ship2Home Logistics Unit | G2766: Delivered | H2766: Debit Card | I2766: App | J2766: 43535.376 | K2766: 43538.376 | L2766: 43541.376 | M2766: =_xlfn.DAYS(Table1[[#This Row],[actual_delivery_date]],Table1[[#This Row],[dispatch_date]]) -> 3 | N2766: 0 | O2766: =Table1[[#This Row],[transit_storage_cost]] * (1-'What -if Analysis'!$D$26) -> 0 | P2766: 123 | Q2766: 2556.6566
A2767: 569184 | B2767: Gaming Console | C2767: Bangalore | D2767: Kolkata | E2767: WB | F2767: FastWheels Ltd | G2767: Delivered | H2767: Debit Card | I2767: Website | J2767: 43531.378 | K2767: 43538.378 | L2767: 43535.378 | M2767: =_xlfn.DAYS(Table1[[#This Row],[actual_delivery_date]],Table1[[#This Row],[dispatch_date]]) -> 7 | N2767: 34 | O2767: =Table1[[#This Row],[transit_storage_cost]] * (1-'What -if Analysis'!$D$26) -> 34 | P2767: 115 | Q2767: 3444
A2768: 879271 | B2768: Mobile | C2768: Delhi | D2768: Mumbai | E2768: MH | F2768: Ship2Home delivery | G2768: Delivered | H2768: Credit Card | I2768: App | J2768: 43532.382 | K2768: 43538.382 | L2768: 43539.382 | M2768: =_xlfn.DAYS(Table1[[#This Row],[actual_delivery_date]],Table1[[#This Row],[dispatch_date]]) -> 6 | N2768: 26 | O2768: =Table1[[#This Row],[transit_storage_cost]] * (1-'What -if Analysis'!$D$26) -> 26 | P2768: 105 | Q2768: 1174.4789
A2769: 307020 | B2769: Gaming Console | C2769: Delhi | D2769: Bangalore | E2769: KA | F2769: FastWheels Ltd | G2769: Delivered | H2769: Debit Card | I2769: Website | J2769: 43536.385 | K2769: 43538.385 | L2769: 43540.385 | M2769: =_xlfn.DAYS(Table1[[#This Row],[actual_delivery_date]],Table1[[#This Row],[dispatch_date]]) -> 2 | N2769: 9999 | O2769: =Table1[[#This Row],[transit_storage_cost]] * (1-'What -if Analysis'!$D$26) -> 9999 | P2769: 102 | Q2769: 2659
A2770: 906928 | B2770: PC | C2770: Delhi | D2770: Kolkata | E2770: WB | F2770: FastWheels Ltd | G2770: Delivered | H2770: Debit Card | I2770: App | J2770: 43532.386 | K2770: 43538.386 | L2770: 43539.386 | M2770: =_xlfn.DAYS(Table1[[#This Row],[actual_delivery_date]],Table1[[#This Row],[dispatch_date]]) -> 6 | N2770: 42 | O2770: =Table1[[#This Row],[transit_storage_cost]] * (1-'What -if Analysis'!$D$26) -> 42 | P2770: 109 | Q2770: 1475.8089
A2771: 892314 | B2771: Laptop | C2771: Bangalore | D2771: Kolkata | E2771: WB | F2771: FastWheels Ltd | G2771: Delivered | H2771: Debit Card | I2771: Website | J2771: 43533.388 | K2771: 43538.388 | L2771: 43537.388 | M2771: =_xlfn.DAYS(Table1[[#This Row],[actual_delivery_date]],Table1[[#This Row],[dispatch_date]]) -> 5 | N2771: 77 | O2771: =Table1[[#This Row],[transit_storage_cost]] * (1-'What -if Analysis'!$D$26) -> 77 | P2771: 92 | Q2771: 2595.4634
A2772: 175603 | B2772: Tablet | C2772: Delhi | D2772: Mumbai | E2772: MH | F2772: FastWheels Ltd | G2772: Delivered | H2772: Credit Card | I2772: App | J2772: 43532.389 | K2772: 43538.389 | L2772: 43535.389 | M2772: =_xlfn.DAYS(Table1[[#This Row],[actual_delivery_date]],Table1[[#This Row],[dispatch_date]]) -> 6 | N2772: 83 | O2772: =Table1[[#This Row],[transit_storage_cost]] * (1-'What -if Analysis'!$D$26) -> 83 | P2772: 87 | Q2772: 1306.1375
A2773: 641253 | B2773: Tablet | C2773: Delhi | D2773: Delhi | E2773: DL | F2773: FastWheels Ltd | G2773: Delivered | H2773: Credit Card | I2773: Website | J2773: 43533.391 | K2773: 43538.391 | L2773: 43536.391 | M2773: =_xlfn.DAYS(Table1[[#This Row],[actual_delivery_date]],Table1[[#This Row],[dispatch_date]]) -> 5 | N2773: 0 | O2773: =Table1[[#This Row],[transit_storage_cost]] * (1-'What -if Analysis'!$D$26) -> 0 | P2773: 110 | Q2773: 3066.6732
A2774: 395384 | B2774: PC | C2774: Bangalore | D2774: Delhi | E2774: DL | F2774: FastWheels Ltd | G2774: Delivered | H2774: Debit Card | I2774: App | J2774: 43536.403 | K2774: 43538.403 | L2774: 43541.403 | M2774: =_xlfn.DAYS(Table1[[#This Row],[actual_delivery_date]],Table1[[#This Row],[dispatch_date]]) -> 2 | N2774: 47 | O2774: =Table1[[#This Row],[transit_storage_cost]] * (1-'What -if Analysis'!$D$26) -> 47 | P2774: 125 | Q2774: 2233
A2775: 310167 | B2775: Tablet | C2775: Bangalore | D2775: Mumbai | E2775: MH | F2775: Ship2Home delivery | G2775: Delivered | H2775: Credit Card | I2775: Website | J2775: 43532.412 | K2775: 43538.412 | L2775: 43538.412 | M2775: =_xlfn.DAYS(Table1[[#This Row],[actual_delivery_date]],Table1[[#This Row],[dispatch_date]]) -> 6 | N2775: 45 | O2775: =Table1[[#This Row],[transit_storage_cost]] * (1-'What -if Analysis'!$D$26) -> 45 | P2775: 106 | Q2775: 2296.6727
A2776: 396696 | B2776: Laptop | C2776: Delhi | D2776: Mumbai | E2776: MH | F2776: FastWheels Ltd | G2776: Delivered | H2776: Debit Card | I2776: Website | J2776: 43536.416 | K2776: 43538.416 | L2776: 43540.416 | M2776: =_xlfn.DAYS(Table1[[#This Row],[actual_delivery_date]],Table1[[#This Row],[dispatch_date]]) -> 2 | N2776: 47 | O2776: =Table1[[#This Row],[transit_storage_cost]] * (1-'What -if Analysis'!$D$26) -> 47 | P2776: 106 | Q2776: 2464
... A2882: 209416 | B2882: Laptop | C2882: Bangalore | D2882: Mumbai | E2882: MH | F2882: FastWheels Ltd | G2882: Delivered | H2882: Debit Card | I2882: App | J2882: 43536.746 | K2882: 43538.746 | L2882: 43541.746 | M2882: =_xlfn.DAYS(Table1[[#This Row],[actual_delivery_date]],Table1[[#This Row],[dispatch_date]]) -> 2 | N2882: 88 | O2882: =Table1[[#This Row],[transit_storage_cost]] * (1-'What -if Analysis'!$D$26) -> 88 | P2882: 93 | Q2882: 603.9124
A2883: 888167 | B2883: Mobile | C2883: Delhi | D2883: Mumbai | E2883: MH | G2883: Delivered | H2883: Cash On Delivery | I2883: App | J2883: 43536.75 | K2883: 43538.75 | L2883: 43541.75 | M2883: =_xlfn.DAYS(Table1[[#This Row],[actual_delivery_date]],Table1[[#This Row],[dispatch_date]]) -> 2 | N2883: 49 | O2883: =Table1[[#This Row],[transit_storage_cost]] * (1-'What -if Analysis'!$D$26) -> 49 | P2883: 107 | Q2883: 2977.1655
A2884: 344461 | B2884: Laptop | C2884: Delhi | D2884: Bangalore | E2884: KA | F2884: FastWheels Ltd | G2884: Delivered | H2884: Credit Card | I2884: App | J2884: 43532.75 | K2884: 43538.75 | L2884: 43539.75 | M2884: =_xlfn.DAYS(Table1[[#This Row],[actual_delivery_date]],Table1[[#This Row],[dispatch_date]]) -> 6 | N2884: 74 | O2884: =Table1[[#This Row],[transit_storage_cost]] * (1-'What -if Analysis'!$D$26) -> 74 | P2884: 105 | Q2884: 1701.6729
A2885: 421332 | B2885: TV | C2885: Bangalore | D2885: Chennai | E2885: TN | F2885: FastWheels Ltd | G2885: Delivered | H2885: Debit Card | I2885: Website | J2885: 43528.766 | K2885: 43538.766 | L2885: 43531.766 | M2885: =_xlfn.DAYS(Table1[[#This Row],[actual_delivery_date]],Table1[[#This Row],[dispatch_date]]) -> 10 | N2885: 65 | O2885: =Table1[[#This Row],[transit_storage_cost]] * (1-'What -if Analysis'!$D$26) -> 65 | P2885: 100 | Q2885: 1042.37
A2886: 502739 | B2886: Tablet | C2886: Delhi | D2886: Bangalore | E2886: KA | F2886: Ship2Home delivery | G2886: Delivered | H2886: Credit Card | I2886: App | J2886: 43528.767 | K2886: 43538.767 | L2886: 43535.767 | M2886: =_xlfn.DAYS(Table1[[#This Row],[actual_delivery_date]],Table1[[#This Row],[dispatch_date]]) -> 10 | N2886: 46 | O2886: =Table1[[#This Row],[transit_storage_cost]] * (1-'What -if Analysis'!$D$26) -> 46 | P2886: 124 | Q2886: 908.23091
A2887: 44404 | B2887: PC | C2887: Bangalore | D2887: Mumbai | E2887: MH | F2887: FastWheels Ltd | G2887: Delivered | H2887: Debit Card | I2887: App | J2887: 43533.767 | K2887: 43538.767 | L2887: 43540.767 | M2887: =_xlfn.DAYS(Table1[[#This Row],[actual_delivery_date]],Table1[[#This Row],[dispatch_date]]) -> 5 | N2887: 38 | O2887: =Table1[[#This Row],[transit_storage_cost]] * (1-'What -if Analysis'!$D$26) -> 38 | P2887: 107 | Q2887: 3492.1823
A2888: 679117 | B2888: Laptop | C2888: Bangalore | D2888: Delhi | E2888: DL | F2888: FastWheels Ltd | G2888: Delivered | H2888: Credit Card | I2888: App | J2888: 43532.769 | K2888: 43538.769 | L2888: 43539.769 | M2888: =_xlfn.DAYS(Table1[[#This Row],[actual_delivery_date]],Table1[[#This Row],[dispatch_date]]) -> 6 | N2888: 67 | O2888: =Table1[[#This Row],[transit_storage_cost]] * (1-'What -if Analysis'!$D$26) -> 67 | P2888: 104 | Q2888: 1231.2746
A2889: 892678 | B2889: PC | C2889: Delhi | D2889: Chennai | E2889: TN | F2889: Ship2Home Logistics Unit | G2889: Delivered | H2889: Debit Card | I2889: App | J2889: 43534.781 | K2889: 43538.781 | L2889: 43540.781 | M2889: =_xlfn.DAYS(Table1[[#This Row],[actual_delivery_date]],Table1[[#This Row],[dispatch_date]]) -> 4 | N2889: 35 | O2889: =Table1[[#This Row],[transit_storage_cost]] * (1-'What -if Analysis'!$D$26) -> 35 | P2889: 129 | Q2889: 3239
A2890: 439516 | B2890: Laptop | C2890: Bangalore | D2890: Mumbai | E2890: MH | F2890: FastWheels Ltd | G2890: Delivered | H2890: Debit Card | I2890: App | J2890: 43532.785 | K2890: 43538.785 | L2890: 43535.785 | M2890: =_xlfn.DAYS(Table1[[#This Row],[actual_delivery_date]],Table1[[#This Row],[dispatch_date]]) -> 6 | N2890: 83 | O2890: =Table1[[#This Row],[transit_storage_cost]] * (1-'What -if Analysis'!$D$26) -> 83 | P2890: 94 | Q2890: 2348.1281
A2891: 671405 | B2891: Mobile | C2891: Bangalore | D2891: Delhi | E2891: DL | F2891: Ship2Home delivery | G2891: Delivered | H2891: Cash On Delivery | I2891: App | J2891: 43535.785 | K2891: 43538.785 | L2891: 43541.785 | M2891: =_xlfn.DAYS(Table1[[#This Row],[actual_delivery_date]],Table1[[#This Row],[dispatch_date]]) -> 3 | N2891: 37 | O2891: =Table1[[#This Row],[transit_storage_cost]] * (1-'What -if Analysis'!$D$26) -> 37 | P2891: 129 | Q2891: 784.50682
A2892: 228742 | B2892: Laptop | C2892: Delhi | D2892: Bangalore | E2892: KA | F2892: Ship2Home Logistics Unit | G2892: Delivered | H2892: Debit Card | I2892: App | J2892: 43530.787 | K2892: 43538.787 | L2892: 43533.787 | M2892: =_xlfn.DAYS(Table1[[#This Row],[actual_delivery_date]],Table1[[#This Row],[dispatch_date]]) -> 8 | N2892: 50 | O2892: =Table1[[#This Row],[transit_storage_cost]] * (1-'What -if Analysis'!$D$26) -> 50 | P2892: 122 | Q2892: 289
A2893: 441189 | B2893: PC | C2893: Delhi | D2893: Delhi | E2893: DL | F2893: Ship2Home delivery | G2893: Delivered | H2893: Cash On Delivery | I2893: Website | J2893: 43537.787 | K2893: 43538.787 | L2893: 43540.787 | M2893: =_xlfn.DAYS(Table1[[#This Row],[actual_delivery_date]],Table1[[#This Row],[dispatch_date]]) -> 1 | N2893: 0 | O2893: =Table1[[#This Row],[transit_storage_cost]] * (1-'What -if Analysis'!$D$26) -> 0 | P2893: 130 | Q2893: 564
A2894: 727793 | B2894: Tablet | C2894: Delhi | D2894: Mumbai | E2894: MH | F2894: Ship2Home delivery | G2894: Delivered | H2894: Credit Card | I2894: App | J2894: 43531.791 | K2894: 43538.791 | L2894: 43534.791 | M2894: =_xlfn.DAYS(Table1[[#This Row],[actual_delivery_date]],Table1[[#This Row],[dispatch_date]]) -> 7 | N2894: 37 | O2894: =Table1[[#This Row],[transit_storage_cost]] * (1-'What -if Analysis'!$D$26) -> 37 | P2894: 111 | Q2894: 3391.731
A2895: 104249 | B2895: Laptop | C2895: Bangalore | D2895: Bangalore | E2895: KA | F2895: Ship2Home delivery | G2895: Delivered | H2895: Credit Card | I2895: App | J2895: 43538.801 | K2895: 43538.801 | L2895: 43542.801 | M2895: =_xlfn.DAYS(Table1[[#This Row],[actual_delivery_date]],Table1[[#This Row],[dispatch_date]]) -> 0 | N2895: 0 | O2895: =Table1[[#This Row],[transit_storage_cost]] * (1-'What -if Analysis'!$D$26) -> 0 | P2895: 128 | Q2895: 302.46858
... A3144: 585781 | B3144: Laptop | C3144: Delhi | D3144: Mumbai | E3144: MH | F3144: Ship2Home delivery | G3144: Delivered | H3144: Cash On Delivery | I3144: App | J3144: 43533.677 | K3144: 43539.677 | L3144: 43537.677 | M3144: =_xlfn.DAYS(Table1[[#This Row],[actual_delivery_date]],Table1[[#This Row],[dispatch_date]]) -> 6 | N3144: 28 | O3144: =Table1[[#This Row],[transit_storage_cost]] * (1-'What -if Analysis'!$D$26) -> 28 | P3144: 106 | Q3144: 1612
A3145: 363819 | B3145: Gaming Console | C3145: Delhi | D3145: Bangalore | E3145: KA | G3145: Delivered | H3145: Credit Card | I3145: Website | J3145: 43537.678 | K3145: 43539.678 | L3145: 43541.678 | M3145: =_xlfn.DAYS(Table1[[#This Row],[actual_delivery_date]],Table1[[#This Row],[dispatch_date]]) -> 2 | N3145: 32 | O3145: =Table1[[#This Row],[transit_storage_cost]] * (1-'What -if Analysis'!$D$26) -> 32 | P3145: 124 | Q3145: 3693.1921
A3146: 228379 | B3146: Tablet | C3146: Delhi | D3146: Bangalore | E3146: KA | F3146: Ship2Home delivery | G3146: Delivered | H3146: Credit Card | I3146: App | J3146: 43531.688 | K3146: 43539.688 | L3146: 43535.688 | M3146: =_xlfn.DAYS(Table1[[#This Row],[actual_delivery_date]],Table1[[#This Row],[dispatch_date]]) -> 8 | N3146: 27 | O3146: =Table1[[#This Row],[transit_storage_cost]] * (1-'What -if Analysis'!$D$26) -> 27 | P3146: 123 | Q3146: 1189.2999
A3147: 779548 | B3147: Mobile | C3147: Delhi | D3147: Bangalore | E3147: KA | F3147: FastWheels Ltd | G3147: Delivered | H3147: Debit Card | I3147: App | J3147: 43537.688 | K3147: 43539.688 | L3147: 43544.688 | M3147: =_xlfn.DAYS(Table1[[#This Row],[actual_delivery_date]],Table1[[#This Row],[dispatch_date]]) -> 2 | N3147: 38 | O3147: =Table1[[#This Row],[transit_storage_cost]] * (1-'What -if Analysis'!$D$26) -> 38 | P3147: 126 | Q3147: 2225.4958
A3148: 485088 | B3148: PC | C3148: Delhi | D3148: Chennai | E3148: TN | F3148: FastWheels Ltd | G3148: Delivered | H3148: Debit Card | I3148: Website | J3148: 43532.698 | K3148: 43539.698 | L3148: 43535.698 | M3148: =_xlfn.DAYS(Table1[[#This Row],[actual_delivery_date]],Table1[[#This Row],[dispatch_date]]) -> 7 | N3148: 49 | O3148: =Table1[[#This Row],[transit_storage_cost]] * (1-'What -if Analysis'!$D$26) -> 49 | P3148: 127 | Q3148: 1492.6817
A3149: 770107 | B3149: Tablet | C3149: Bangalore | D3149: Mumbai | E3149: MH | F3149: FastWheels Ltd | G3149: Delivered | H3149: Credit Card | I3149: App | J3149: 43535.698 | K3149: 43539.698 | L3149: 43542.698 | M3149: =_xlfn.DAYS(Table1[[#This Row],[actual_delivery_date]],Table1[[#This Row],[dispatch_date]]) -> 4 | N3149: 67 | O3149: =Table1[[#This Row],[transit_storage_cost]] * (1-'What -if Analysis'!$D$26) -> 67 | P3149: 93 | Q3149: 3368.3289
A3150: 230792 | B3150: Laptop | C3150: Delhi | D3150: Chennai | E3150: TN | F3150: FastWheels Ltd | G3150: Delivered | H3150: Debit Card | I3150: App | J3150: 43528.698 | K3150: 43539.698 | L3150: 43533.698 | M3150: =_xlfn.DAYS(Table1[[#This Row],[actual_delivery_date]],Table1[[#This Row],[dispatch_date]]) -> 11 | N3150: 41 | O3150: =Table1[[#This Row],[transit_storage_cost]] * (1-'What -if Analysis'!$D$26) -> 41 | P3150: 122 | Q3150: 947.7587
A3151: 484459 | B3151: PC | C3151: Delhi | D3151: Mumbai | E3151: MH | F3151: FastWheels Ltd | G3151: Delivered | H3151: Credit Card | I3151: App | J3151: 43537.727 | K3151: 43539.727 | L3151: 43543.727 | M3151: =_xlfn.DAYS(Table1[[#This Row],[actual_delivery_date]],Table1[[#This Row],[dispatch_date]]) -> 2 | N3151: 73 | O3151: =Table1[[#This Row],[transit_storage_cost]] * (1-'What -if Analysis'!$D$26) -> 73 | P3151: 89 | Q3151: 1120.3349
A3152: 882741 | B3152: Laptop | C3152: Bangalore | D3152: Kolkata | E3152: WB | F3152: Ship2Home delivery | G3152: Delivered | H3152: Credit Card | I3152: Website | J3152: 43537.729 | K3152: 43539.729 | L3152: 43543.729 | M3152: =_xlfn.DAYS(Table1[[#This Row],[actual_delivery_date]],Table1[[#This Row],[dispatch_date]]) -> 2 | N3152: 45 | O3152: =Table1[[#This Row],[transit_storage_cost]] * (1-'What -if Analysis'!$D$26) -> 45 | P3152: 107 | Q3152: 441.26487
A3153: 749799 | B3153: Mobile | C3153: Delhi | D3153: Bangalore | E3153: KA | F3153: Ship2Home delivery | G3153: Delivered | H3153: Credit Card | I3153: Website | J3153: 43531.73 | K3153: 43539.73 | L3153: 43538.73 | M3153: =_xlfn.DAYS(Table1[[#This Row],[actual_delivery_date]],Table1[[#This Row],[dispatch_date]]) -> 8 | N3153: 35 | O3153: =Table1[[#This Row],[transit_storage_cost]] * (1-'What -if Analysis'!$D$26) -> 35 | P3153: 127 | Q3153: 3381.6558
A3154: 506957 | B3154: Mobile | C3154: Delhi | D3154: Mumbai | E3154: MH | F3154: FastWheels Ltd | G3154: Delivered | H3154: Credit Card | I3154: App | J3154: 43537.733 | K3154: 43539.733 | L3154: 43544.733 | M3154: =_xlfn.DAYS(Table1[[#This Row],[actual_delivery_date]],Table1[[#This Row],[dispatch_date]]) -> 2 | N3154: 81 | O3154: =Table1[[#This Row],[transit_storage_cost]] * (1-'What -if Analysis'!$D$26) -> 81 | P3154: 90 | Q3154: 3233.5824
A3155: 197518 | B3155: Tablet | C3155: Delhi | D3155: Kolkata | E3155: WB | F3155: FastWheels Ltd | G3155: Delivered | H3155: Debit Card | I3155: App | J3155: 43532.736 | K3155: 43539.736 | L3155: 43537.736 | M3155: =_xlfn.DAYS(Table1[[#This Row],[actual_delivery_date]],Table1[[#This Row],[dispatch_date]]) -> 7 | N3155: 76 | O3155: =Table1[[#This Row],[transit_storage_cost]] * (1-'What -if Analysis'!$D$26) -> 76 | P3155: 95 | Q3155: 2028.7881
A3156: 779404 | B3156: Tablet | C3156: Bangalore | D3156: Chennai | E3156: TN | F3156: FastWheels Ltd | G3156: Delivered | H3156: Debit Card | I3156: App | J3156: 43532.747 | K3156: 43539.747 | L3156: 43537.747 | M3156: =_xlfn.DAYS(Table1[[#This Row],[actual_delivery_date]],Table1[[#This Row],[dispatch_date]]) -> 7 | N3156: 28 | O3156: =Table1[[#This Row],[transit_storage_cost]] * (1-'What -if Analysis'!$D$26) -> 28 | P3156: 122 | Q3156: 3479.9873
A3157: 694400 | B3157: Laptop | C3157: Delhi | D3157: Kolkata | E3157: WB | F3157: FastWheels Ltd | G3157: Delivered | H3157: Debit Card | I3157: App | J3157: 43536.75 | K3157: 43539.75 | L3157: 43542.75 | M3157: =_xlfn.DAYS(Table1[[#This Row],[actual_delivery_date]],Table1[[#This Row],[dispatch_date]]) -> 3 | N3157: 35 | O3157: =Table1[[#This Row],[transit_storage_cost]] * (1-'What -if Analysis'!$D$26) -> 35 | P3157: 113 | Q3157: 304
... A4298: 449427 | B4298: Tablet | C4298: Delhi | D4298: Chennai | E4298: TN | F4298: FastWheels Ltd | G4298: Delivered | H4298: Credit Card | I4298: Website | J4298: 43538.334 | K4298: 43549.334 | L4298: 43544.334 | M4298: =_xlfn.DAYS(Table1[[#This Row],[actual_delivery_date]],Table1[[#This Row],[dispatch_date]]) -> 11 | N4298: 73 | O4298: =Table1[[#This Row],[transit_storage_cost]] * (1-'What -if Analysis'!$D$26) -> 73 | P4298: 104 | Q4298: 803.27731

Sheet Data Understanding

Sheet Descriptive Statistics
D10: Metrics | E10: Delivery Days | F10: transit_storage_cost | G10: shipping_cost | H10: Session_length
D11: Median | E11: =MEDIAN(Table1[Delivery Days]) -> 4 | F11: =MEDIAN(Table1[transit_storage_cost]) -> 37 | G11: =MEDIAN(Table1[shipping_cost]) -> 112 | H11: =MEDIAN(Table1[Session_length]) -> 1988.4188
D12: Average | E12: =AVERAGE(Table1[Delivery Days]) -> 4.5701652 | F12: =AVERAGE(Table1[transit_storage_cost]) -> 87.286712 | G12: =AVERAGE(Table1[shipping_cost]) -> 113.29788 | H12: =AVERAGE(Table1[Session_length]) -> 1990.0856
D13: Minimum | E13: =MIN(Table1[Delivery Days]) -> 0 | F13: =MIN(Table1[transit_storage_cost]) -> 0 | G13: =MIN(Table1[shipping_cost]) -> 85 | H13: =MIN(Table1[Session_length]) -> -1
D14: Maximum | E14: =MAX(Table1[Delivery Days]) -> 11 | F14: =MAX(Table1[transit_storage_cost]) -> 9999 | G14: =MAX(Table1[shipping_cost]) -> 130 | H14: =MAX(Table1[Session_length]) -> 3877.9825
D15: St.Dev | E15: =_xlfn.STDEV.P(Table1[Delivery Days]) -> 2.4336241 | F15: =_xlfn.STDEV.P(Table1[transit_storage_cost]) -> 711.48314 | G15: =_xlfn.STDEV.P(Table1[shipping_cost]) -> 11.896524 | H15: =_xlfn.STDEV.P(Table1[Session_length]) -> 1005.8906
D16: Variane | E16: =_xlfn.VAR.P(Table1[Delivery Days]) -> 5.9225262 | F16: =_xlfn.VAR.P(Table1[transit_storage_cost]) -> 506208.26 | G16: =_xlfn.VAR.P(Table1[shipping_cost]) -> 141.52728 | H16: =_xlfn.VAR.P(Table1[Session_length]) -> 1011815.9
D17: Count | E17: =COUNT(Table1[Delivery Days]) -> 4297 | F17: =COUNT(Table1[transit_storage_cost]) -> 4297 | G17: =COUNT(Table1[shipping_cost]) -> 4297 | H17: =COUNT(Table1[Session_length]) -> 4297
D18: Skewness | E18: =SKEW(Table1[Delivery Days]) -> 0.25308484 | F18: =SKEW(Table1[transit_storage_cost]) -> 13.846545 | G18: =SKEW(Table1[shipping_cost]) -> -0.4900254 | H18: =SKEW(Table1[Session_length]) -> 0.0076774036

Sheet Pivot Table Analysis
B9: Product Category | C9: Average of shipping_cost | E9: Product Category | F9: Count of order_id
B10: Gaming Console | C10: 113.61377 | E10: Gaming Console | F10: 334
B11: Laptop | C11: 113.00875 | E11: Laptop | F11: 1029
B12: Mobile | C12: 112.97994 | E12: Mobile | F12: 1246
B13: PC | C13: 113.80267 | E13: PC | F13: 674
B14: Tablet | C14: 113.64017 | E14: Tablet | F14: 478
B15: TV | C15: 113.36106 | E15: TV | F15: 529
B16: Grand Total | C16: 113.28601 | E16: Grand Total | F16: 4290
B23: final_delivery_status | C23: Delivered | E23: final_delivery_status | F23: Delivered
B25: Logistics Provider | C25: Average of Delivery Days | E25: Logistics Provider | F25: Count of order_id
B26: FastWheels Ltd | C26: 4.035288 | E26: FastWheels Ltd | F26: 1927
B27: Ship2Home delivery | C27: 5.0809555 | E27: Ship2Home delivery | F27: 1507
B28: Ship2Home Logistics Unit | C28: 4.9690027 | E28: Ship2Home Logistics Unit | F28: 742
B29: Grand Total | C29: 4.5785441 | E29: Grand Total | F29: 4176
B39: Count of order_id | C39: Sources
B40: Payment Mode | C40: Cash On Delivery | D40: Credit Card | E40: Debit Card | F40: Grand Total
B41: App | C41: 197 | D41: 1228 | E41: 1441 | F41: 2866
B42: Website | C42: 121 | D42: 590 | E42: 713 | F42: 1424
B43: Grand Total | C43: 318 | D43: 1818 | E43: 2154 | F43: 4290
B52: Destination City | C52: Average of shipping_cost | D52: Average of transit_storage_cost | F52: Destination City | G52: Count of order_id
B53: Bangalore | C53: 119.04357 | D53: 82.617647 | F53: Bangalore | G53: 918
B54: Chennai | C54: 119.73239 | D54: 63.746479 | F54: Chennai | G54: 568
B55: Delhi | C55: 118.97124 | D55: 94.584416 | F55: Delhi | G55: 1078
B56: Kolkata | C56: 104.58947 | D56: 98.982456 | F56: Kolkata | G56: 570
B57: Mumbai | C57: 104.53287 | D57: 90.314879 | F57: Mumbai | G57: 1156
B58: Grand Total | C58: 113.28601 | D58: 87.374592 | F58: Grand Total | G58: 4290
B66: Delivery Days | C66: Count of order_id | D66: Average of Session_length
B67: 0 | C67: 165 | D67: 2076.2795
B68: 1 | C68: 148 | D68: 1828.3905
B69: 2 | C69: 746 | D69: 1958.1725
B70: 3 | C70: 513 | D70: 1970.9796
B71: 4 | C71: 585 | D71: 2017.1097
B72: 5 | C72: 613 | D72: 2040.8704
B73: 6 | C73: 563 | D73: 1981.6907
B74: 7 | C74: 420 | D74: 1996.2255
B75: 8 | C75: 232 | D75: 2018.6251
B76: 9 | C76: 202 | D76: 1962.2606
B77: 10 | C77: 85 | D77: 1893.9336
B78: 11 | C78: 18 | D78: 2173.2961
B79: Grand Total | C79: 4290 | D79: 1989.5263

Sheet What -if Analysis
C13: Shipping Cost Increase % | D13: Shipping Cost
C14: 0 | D14: =AVERAGE(Table1[shipping_cost])*(1+C14) -> 113.29788
C15: 0.05 | D15: 118.96278
C16: 0.1 | D16: 124.62767
C17: 0.15 | D17: 130.29256
C24: Transit Storage Cost | D24: 28
C25: Improved Transit Storage Cost | D25: =$D$24*(1-D26) -> 28
C26: Storage Reduction | D26: 0
C32: Average Delivery Days | D32: =AVERAGE(Table1[Delivery Days]) -> 4.5701652
C33: Average Session length | D33: =AVERAGE(Table1[Session_length]) -> 1990.0856
C34: Delivery Impact Factor | D34: -335544.32
C35: Improved Session Length | D35: =D33*(1+D34) -> -6.6775993e+08
C36: Target Delivery Days | D36: =D32-2 -> 2.5701652

Sheet Scenario Summary
B2: Scenario Summary
D3: Current Values: | E3: Optimized
E4: Created by Sarthak Somani on 08-01-2026 Modified by Sarthak Somani on 08-01-2026
B5: Changing Cells:
C6: $D$21 | D6: 0 | E6: 0.2
B7: Result Cells:
C8: $D$20 | D8: 28 | E8: 22.4
B9: Notes: Current Values column represents values of changing cells at
B10: time Scenario Summary Report was created. Changing cells for each
B11: scenario are highlighted in gray.

Sheet Data Visualization 

Sheet Forecast
A1: Delivery Days | B1: shipping_cost | C1: Forecast(shipping_cost) | D1: Lower Confidence Bound(shipping_cost) | E1: Upper Confidence Bound(shipping_cost)
A2: 0 | B2: 114.1697
A3: 1 | B3: 118.70946
A4: 2 | B4: 110.45551
A5: 3 | B5: 113.02144
A6: 4 | B6: 113.05128
A7: 5 | B7: 113.12561
A8: 6 | B8: 113.80639
A9: 7 | B9: 114.38095
A10: 8 | B10: 113.81034
A11: 9 | B11: 114.53465
A12: 10 | B12: 118.77647
A13: 11 | B13: 113.94444 | C13: 113.94444 | D13: 113.94444 | E13: 113.94444
A14: 12 | C14: =_xlfn.FORECAST.ETS(A14,$B$2:$B$13,$A$2:$A$13,1,1) -> 115.63369 | D14: =C14-_xlfn.FORECAST.ETS.CONFINT(A14,$B$2:$B$13,$A$2:$A$13,0.95,1,1) -> 112.07779 | E14: =C14+_xlfn.FORECAST.ETS.CONFINT(A14,$B$2:$B$13,$A$2:$A$13,0.95,1,1) -> 119.18959
A15: 13 | C15: =_xlfn.FORECAST.ETS(A15,$B$2:$B$13,$A$2:$A$13,1,1) -> 117.99768 | D15: =C15-_xlfn.FORECAST.ETS.CONFINT(A15,$B$2:$B$13,$A$2:$A$13,0.95,1,1) -> 114.41322 | E15: =C15+_xlfn.FORECAST.ETS.CONFINT(A15,$B$2:$B$13,$A$2:$A$13,0.95,1,1) -> 121.58215
A16: 14 | C16: =_xlfn.FORECAST.ETS(A16,$B$2:$B$13,$A$2:$A$13,1,1) -> 113.96908 | D16: =C16-_xlfn.FORECAST.ETS.CONFINT(A16,$B$2:$B$13,$A$2:$A$13,0.95,1,1) -> 110.35583 | E16: =C16+_xlfn.FORECAST.ETS.CONFINT(A16,$B$2:$B$13,$A$2:$A$13,0.95,1,1) -> 117.58233
A17: 15 | C17: =_xlfn.FORECAST.ETS(A17,$B$2:$B$13,$A$2:$A$13,1,1) -> 116.15789 | D17: =C17-_xlfn.FORECAST.ETS.CONFINT(A17,$B$2:$B$13,$A$2:$A$13,0.95,1,1) -> 112.51519 | E17: =C17+_xlfn.FORECAST.ETS.CONFINT(A17,$B$2:$B$13,$A$2:$A$13,0.95,1,1) -> 119.80059
A18: 16 | C18: =_xlfn.FORECAST.ETS(A18,$B$2:$B$13,$A$2:$A$13,1,1) -> 118.52188 | D18: =C18-_xlfn.FORECAST.ETS.CONFINT(A18,$B$2:$B$13,$A$2:$A$13,0.95,1,1) -> 114.84997 | E18: =C18+_xlfn.FORECAST.ETS.CONFINT(A18,$B$2:$B$13,$A$2:$A$13,0.95,1,1) -> 122.1938
A19: 17 | C19: =_xlfn.FORECAST.ETS(A19,$B$2:$B$13,$A$2:$A$13,1,1) -> 114.49328 | D19: =C19-_xlfn.FORECAST.ETS.CONFINT(A19,$B$2:$B$13,$A$2:$A$13,0.95,1,1) -> 110.79194 | E19: =C19+_xlfn.FORECAST.ETS.CONFINT(A19,$B$2:$B$13,$A$2:$A$13,0.95,1,1) -> 118.19462

Sheet Dashboard 
F9: KPI's | G9: Values
B10: Average Delivery Days | F10: Average Delivery Days | G10: =AVERAGE(Table1[Delivery Days]) -> 4.5701652 | I10: Average Shipping Cost
F11: Average Shipping Cost | G11: =AVERAGE(Table1[shipping_cost]) -> 113.29788
F12: Average Transit Cost | G12: =AVERAGE(Table1[transit_storage_cost]) -> 87.286712
F13: Average Session Length | G13: =AVERAGE(Table1[Session_length]) -> 1990.0856
F14: Highest Transit Cost | G14: =MAX(Table1[transit_storage_cost]) -> 9999
F15: Max Shipping Days | G15: =MAX(Table1[Delivery Days]) -> 11
F16: Highest Shipping Cost | G16: =MAX(Table1[shipping_cost]) -> 130
B18: Average Transit Cost | I18: Average Session length
F23: Highest Shipping Cost
B25: Highest Transit Cost | I25: Max Shipping Days

Sheet Insights
